{
  "namespace": "simple-firebase-components",
  "components": [
    [
      "fb-content-editor",
      [
        "0wdoql4t",
        "dliskmsn"
      ],
      0,
      [
        [
          "doc",
          1,
          1,
          1
        ],
        [
          "id",
          1,
          1,
          1
        ],
        [
          "key",
          1,
          1,
          1
        ]
      ]
    ],
    [
      "fb-string",
      [
        "0wdoql4t",
        "dliskmsn"
      ],
      0,
      [
        [
          "id",
          1,
          1,
          1
        ],
        [
          "item",
          1,
          1,
          2
        ],
        [
          "key",
          1,
          1,
          1
        ]
      ]
    ],
    [
      "stencil-async-content",
      [
        "tf9wp1v6",
        "r1ppdozx"
      ],
      0,
      [
        [
          "content",
          5
        ],
        [
          "documentLocation",
          1,
          1,
          2
        ]
      ]
    ],
    [
      "stencil-route",
      [
        "tf9wp1v6",
        "r1ppdozx"
      ],
      0,
      [
        [
          "activeRouter",
          3,
          0,
          0,
          "activeRouter"
        ],
        [
          "component",
          1,
          1,
          2
        ],
        [
          "componentProps",
          1,
          1,
          1
        ],
        [
          "exact",
          1,
          1,
          3
        ],
        [
          "group",
          1,
          1,
          2
        ],
        [
          "location",
          3,
          0,
          0,
          "location"
        ],
        [
          "match",
          5
        ],
        [
          "routeRender",
          1,
          1,
          1
        ],
        [
          "url",
          1,
          1,
          1
        ]
      ]
    ],
    [
      "stencil-route-link",
      [
        "tf9wp1v6",
        "r1ppdozx"
      ],
      0,
      [
        [
          "activeClass",
          1,
          1,
          2
        ],
        [
          "activeRouter",
          3,
          0,
          0,
          "activeRouter"
        ],
        [
          "custom",
          1,
          1,
          3
        ],
        [
          "exact",
          1,
          1,
          3
        ],
        [
          "location",
          3,
          0,
          0,
          "location"
        ],
        [
          "match",
          5
        ],
        [
          "url",
          1,
          1,
          2
        ],
        [
          "urlMatch",
          1,
          1,
          1
        ]
      ],
      0,
      1
    ],
    [
      "stencil-route-title",
      [
        "tf9wp1v6",
        "r1ppdozx"
      ],
      0,
      [
        [
          "activeRouter",
          3,
          0,
          0,
          "activeRouter"
        ],
        [
          "title",
          1,
          1,
          2
        ]
      ]
    ],
    [
      "stencil-router",
      [
        "tf9wp1v6",
        "r1ppdozx"
      ],
      0,
      [
        [
          "activeRouter",
          3,
          0,
          0,
          "activeRouter"
        ],
        [
          "match",
          5
        ],
        [
          "root",
          1,
          1,
          2
        ],
        [
          "titleSuffix",
          1,
          1,
          2
        ]
      ],
      0,
      1
    ],
    [
      "stencil-router-redirect",
      [
        "tf9wp1v6",
        "r1ppdozx"
      ],
      0,
      [
        [
          "activeRouter",
          3,
          0,
          0,
          "activeRouter"
        ],
        [
          "url",
          1,
          1,
          2
        ]
      ]
    ],
    [
      "test-app",
      [
        "qxjbm44c",
        "1ozgx99l"
      ]
    ],
    [
      "test-demo-four",
      [
        "qxjbm44c",
        "1ozgx99l"
      ],
      0,
      [
        [
          "history",
          1,
          1,
          1
        ],
        [
          "match",
          1,
          1,
          1
        ],
        [
          "pages",
          1,
          1,
          1
        ]
      ]
    ],
    [
      "test-demo-six",
      [
        "qxjbm44c",
        "1ozgx99l"
      ],
      0,
      [
        [
          "history",
          1,
          1,
          1
        ],
        [
          "match",
          1,
          1,
          1
        ],
        [
          "pages",
          1,
          1,
          1
        ]
      ]
    ],
    [
      "test-demo-three",
      [
        "qxjbm44c",
        "1ozgx99l"
      ],
      0,
      [
        [
          "history",
          1,
          1,
          1
        ],
        [
          "match",
          1,
          1,
          1
        ],
        [
          "pages",
          1,
          1,
          1
        ]
      ]
    ]
  ],
  "global": "simple-firebase-components.global.js",
  "core": "simple-firebase-components.aptleq4c.js",
  "coreSsr": "simple-firebase-components.zkdim8zg.js",
  "corePolyfilled": "simple-firebase-components.cqprkifl.js"
}